lineditor/__init__.py
lineditor/editor.py
lineditor-0.1.1.dist-info/LICENSE
lineditor-0.1.1.dist-info/METADATA
lineditor-0.1.1.dist-info/WHEEL
lineditor-0.1.1.dist-info/top_level.txt
lineditor-0.1.1.dist-info/RECORD
