Metadata-Version: 2.1
Name: lineditor
Version: 0.1.1
Summary: Simple library to edit or read text of specific line.
Home-page: https://github.com/mafusuke/lineditor
Author: mafu
Author-email: mafusukee@gmail.com
License: UNKNOWN
Platform: UNKNOWN
Classifier: Programming Language :: Python :: 3.5
Classifier: Programming Language :: Python :: 3.6
Classifier: Programming Language :: Python :: 3.7
Classifier: Programming Language :: Python :: 3.8
Classifier: Programming Language :: Python :: 3.9
Classifier: License :: OSI Approved :: MIT License
Classifier: Operating System :: OS Independent
